cobs.bin
cobs_index.cpython-39-darwin.so
cobs_reloaded-0.1.1.dist-info/RECORD
cobs_reloaded-0.1.1.dist-info/LICENSE
cobs_reloaded-0.1.1.dist-info/AUTHORS
cobs_reloaded-0.1.1.dist-info/WHEEL
cobs_reloaded-0.1.1.dist-info/top_level.txt
cobs_reloaded-0.1.1.dist-info/METADATA
cobs_reloaded-0.1.1.data/scripts/cobs
