Metadata-Version: 2.1
Name: cobs_reloaded
Version: 0.1.1
Summary: Compact Bit-Sliced Signature Index (COBS)
Author: Adrian Romberg
Author-email: adrian.romberg@stud.uni-frankfurt.de
Classifier: Development Status :: 4 - Beta
Classifier: Topic :: Scientific/Engineering :: Bio-Informatics
Classifier: Topic :: Text Processing :: Indexing
Requires-Python: >=3.9
License-File: LICENSE
License-File: AUTHORS
